{
    "id": "IMM-5u010-0001924",
    "permalink": "https://www.lombardiabeniculturali.it/fotografie/schede/IMM-5u010-0001924",
    "description": "Istituto dei Ciechi di Milano - Visita del Sindaco di Milano Gabriele Albertini - Sala Stoppani - Interno - Incontro con il Sindaco - Stretta di mano tra il Sindaco e Raffaele Cattaneo (?) della Regione Lombardia\nAl tavolo della presidenza: Raffaele Cattaneo (?) della Regione Lombardia, il Commissario Rodolfo Masto, il Sindaco Gabriele Albertini",
    "category": "reportage",
    "tags": [
        "assistenza",
        "politica",
        "interni",
        "comunicazione"
    ],
    "year": "1998",
    "filename": "SC_F_SUP-5u010-0002073_IMG-0000784757.jpg"
}