{
    "id": "IMM-5u010-0000522",
    "permalink": "https://www.lombardiabeniculturali.it/fotografie/schede/IMM-5u010-0000522",
    "description": "Istituto dei Ciechi di Milano - Inaugurazione dell'anno scolastico e centenario dalla morte del fondatore dell'Istituto Michele Barozzi\nCappella - Interno - Celebrazione della messa - Navata - Partecipanti alla messa genuflessi - Allievi dell'istituto",
    "category": "reportage",
    "tags": [
        "interni",
        "luoghi di culto",
        "religione"
    ],
    "year": "1967/11/26",
    "filename": "SC_F_SUP-5u010-0000587_IMG-0000783270.jpg"
}