{
    "id": "IMM-5u010-0000946",
    "permalink": "https://www.lombardiabeniculturali.it/fotografie/schede/IMM-5u010-0000946",
    "description": "Istituto dei Ciechi di Milano - Scuola elementare - Aula - Interno - Lezione - Esercizio di scrittura - Ritratto infantile - Bambina - Pinuccia Manenti",
    "category": "reportage",
    "tags": [
        "istruzione",
        "assistenza",
        "infanzia",
        "interni",
        "comunicazione",
        "linguaggi"
    ],
    "year": "1955/05/01",
    "filename": "SC_F_SUP-5u010-0001035_IMG-0000783718.jpg"
}