{
    "id": "IMM-5u010-0001645",
    "permalink": "https://www.lombardiabeniculturali.it/fotografie/schede/IMM-5u010-0001645",
    "description": "Istituto dei Ciechi di Milano - Sala Barozzi - Interno - Commemorazione dell'Unione Italiana Ciechi - Tavolo della presidenza con relatori, al centro Dario Formigoni",
    "category": "reportage",
    "tags": [
        "interni",
        "assistenza",
        "comunicazione"
    ],
    "year": "1960",
    "filename": "SC_F_SUP-5u010-0001778_IMG-0000784462.jpg"
}