{
    "id": "IMM-5u010-0001783",
    "permalink": "https://www.lombardiabeniculturali.it/fotografie/schede/IMM-5u010-0001783",
    "description": "Istituto dei Ciechi di Milano - Visita del Prefetto di Milano Roberto Sorge - Sala Barozzi - Interno - Esposizione di manufatti realizzati dagli allievi dell'Istituto - Ritratto maschile - Allievo dell'Istituto con oggetti in legno",
    "category": "reportage\nritratto",
    "tags": [
        "assistenza",
        "interni",
        "artigianato",
        "biografia / ritratto",
        "giovani"
    ],
    "year": "1997",
    "filename": "SC_F_SUP-5u010-0001916_IMG-0000784600.jpg"
}