{
    "id": "IMM-5u010-0000981",
    "permalink": "https://www.lombardiabeniculturali.it/fotografie/schede/IMM-5u010-0000981",
    "description": "Istituto dei Ciechi di Milano - Sala dei concerti Barozzi - Interno - Inaugurazione dell'anno scolastico - Palco - Discorso di Monsignor Carlo Marcora",
    "category": "reportage\nritratto",
    "tags": [
        "interni",
        "spettacolo",
        "istruzione",
        "assistenza",
        "religione",
        "comunicazione"
    ],
    "year": "1969/11/16",
    "filename": "SC_F_SUP-5u010-0001073_IMG-0000783756.jpg"
}