{
    "id": "IMM-5u010-0000755",
    "permalink": "https://www.lombardiabeniculturali.it/fotografie/schede/IMM-5u010-0000755",
    "description": "Istituto dei Ciechi di Milano - Scuola materna - Interno - Lavoro di manualit\u00e0 con la creta - Bambini - Grembiule",
    "category": "reportage",
    "tags": [
        "interni",
        "istruzione",
        "assistenza",
        "infanzia",
        "abbigliamento",
        "gioco"
    ],
    "year": "1965",
    "filename": "SC_F_SUP-5u010-0000831_IMG-0000783514.jpg"
}