{
    "id": "IMM-5u010-0001695",
    "permalink": "https://www.lombardiabeniculturali.it/fotografie/schede/IMM-5u010-0001695",
    "description": "Istituto dei Ciechi di Milano - Visita del Presidente della Repubblica Scalfaro - Il Commissario Rodolfo Masto accoglie Oscar Luigi Scalfaro davanti all'ingresso - Fotografi",
    "category": "reportage",
    "tags": [
        "socializzazione",
        "politica",
        "assistenza"
    ],
    "year": "1996",
    "filename": "SC_F_SUP-5u010-0001828_IMG-0000784512.jpg"
}