{
    "id": "IMM-5u010-0001720",
    "permalink": "https://www.lombardiabeniculturali.it/fotografie/schede/IMM-5u010-0001720",
    "description": "Fiera di Milano - Stand dell'Istituto dei Ciechi di Milano - Esposizione di manufatti realizzati da ciechi - Il direttore scientifico dell'Istituto Giancarlo Abba parla al pubblico",
    "category": "reportage",
    "tags": [
        "assistenza",
        "fiere",
        "interni",
        "comunicazione",
        "artigianato"
    ],
    "year": "1996",
    "filename": "SC_F_SUP-5u010-0001853_IMG-0000784537.jpg"
}